meer_tec/__init__.py
meer_tec/_version.py
meer_tec/interfaces.py
meer_tec/mecom.py
meer_tec/tec.py
meer_tec-1.0.0.dist-info/LICENSE
meer_tec-1.0.0.dist-info/METADATA
meer_tec-1.0.0.dist-info/WHEEL
meer_tec-1.0.0.dist-info/top_level.txt
meer_tec-1.0.0.dist-info/RECORD
