Metadata-Version: 2.1
Name: meer-tec
Version: 1.0.0
Summary: MeCom for Python
Author: Bastian Leykauf
Author-email: leykauf@physik.hu-berlin.de
License: GNU GENERAL PUBLIC LICENSE
Project-URL: homepage, https://github.com/bleykauf/meer_tec/
Project-URL: repository, https://github.com/bleykauf/meer_tec/
Classifier: Programming Language :: Python :: 3
Classifier: License :: OSI Approved :: GNU General Public License v3 (GPLv3)
Classifier: Operating System :: OS Independent
Classifier: Intended Audience :: Science/Research
Requires-Python: >=3.8
License-File: LICENSE
Requires-Dist: pythoncrc >=0.10.0
Requires-Dist: pyserial >=3.5
Provides-Extra: dev
Requires-Dist: black >=23.11.0 ; extra == 'dev'
Requires-Dist: pre-commit >=2.20.0 ; extra == 'dev'
Requires-Dist: flake8 >=5.0.4 ; extra == 'dev'
Requires-Dist: isort >=5.10.1 ; extra == 'dev'
Requires-Dist: Flake8-pyproject >=1.1.0.post0 ; extra == 'dev'
Requires-Dist: setuptools-scm >=6.2 ; extra == 'dev'
Provides-Extra: tests
Requires-Dist: mypy >=1.7.1 ; extra == 'tests'
Requires-Dist: pytest >=7.4.3 ; extra == 'tests'
Requires-Dist: types-pyserial >=3.5 ; extra == 'tests'
